{"name": "Sulthanbathery", "lsg_code": "272911", "district": "Wayanad", "state": "Kerala", "no_of_wards": 35, "wards": [{"ward_no": "21", "ward_name": "Maithanikunnu", "ward_id": "1294617"}, {"ward_no": "2", "ward_name": "Chethalayam", "ward_id": "1294598"}, {"ward_no": "4", "ward_name": "Vengoor North", "ward_id": "1294600"}, {"ward_no": "33", "ward_name": "Mandan kolli", "ward_id": "1294629"}, {"ward_no": "11", "ward_name": "Kidangil", "ward_id": "1294607"}, {"ward_no": "7", "ward_name": "Pazhayari", "ward_id": "1294603"}, {"ward_no": "6", "ward_name": "Vengoor South", "ward_id": "1294602"}, {"ward_no": "31", "ward_name": "Puthikkadu", "ward_id": "1294627"}, {"ward_no": "30", "ward_name": "Beenachi", "ward_id": "1294626"}, {"ward_no": "9", "ward_name": "Armadu", "ward_id": "1294605"}, {"ward_no": "15", "ward_name": "Sathram Kunnu", "ward_id": "1294611"}, {"ward_no": "13", "ward_name": "Thirunelli", "ward_id": "1294609"}, {"ward_no": "27", "ward_name": "Kalluvayal", "ward_id": "1294623"}, {"ward_no": "12", "ward_name": "Kuppadi", "ward_id": "1294608"}, {"ward_no": "8", "ward_name": "Karuvallikuunnu", "ward_id": "1294604"}, {"ward_no": "34", "ward_name": "Pazhupathoor", "ward_id": "1294630"}, {"ward_no": "5", "ward_name": "Odappallam", "ward_id": "1294601"}, {"ward_no": "35", "ward_name": "Kaivattamoola", "ward_id": "1294631"}, {"ward_no": "24", "ward_name": "Suthan Bathery", "ward_id": "1294620"}, {"ward_no": "16", "ward_name": "Cheroor Kunnu", "ward_id": "1294612"}, {"ward_no": "20", "ward_name": "Kaipancheri", "ward_id": "1294616"}, {"ward_no": "17", "ward_name": "Palakkara", "ward_id": "1294613"}, {"ward_no": "32", "ward_name": "Chinappullu", "ward_id": "1294628"}, {"ward_no": "23", "ward_name": "Kattayadu", "ward_id": "1294619"}, {"ward_no": "3", "ward_name": "Chenad", "ward_id": "1294599"}, {"ward_no": "29", "ward_name": "Dottappankulam", "ward_id": "1294625"}, {"ward_no": "19", "ward_name": "Thoduvetty", "ward_id": "1294615"}, {"ward_no": "26", "ward_name": "Manichira", "ward_id": "1294622"}, {"ward_no": "1", "ward_name": "Aram Mile", "ward_id": "1294597"}, {"ward_no": "22", "ward_name": "Fairland", "ward_id": "1294618"}, {"ward_no": "25", "ward_name": "Pallikki", "ward_id": "1294621"}, {"ward_no": "28", "ward_name": "Poomala", "ward_id": "1294624"}, {"ward_no": "18", "ward_name": "Thelampatta", "ward_id": "1294614"}, {"ward_no": "14", "ward_name": "Mandikkunnu", "ward_id": "1294610"}, {"ward_no": "10", "ward_name": "Kottakkunnu", "ward_id": "1294606"}]}